pycudacov/__init__.py
pycudacov_pkg/__init__.py
pycudacov-0.1.2.dist-info/LICENSE
pycudacov-0.1.2.dist-info/METADATA
pycudacov-0.1.2.dist-info/WHEEL
pycudacov-0.1.2.dist-info/top_level.txt
pycudacov-0.1.2.dist-info/RECORD
